{
  "rules": [
    {
      "name": "rule_market_empty",
      "expected_result": "Verified",
      "prover_options": [],
      "cargo_features": []
    },
    {
      "name": "rule_market_deposit",
      "expected_result": "Verified",
      "prover_options": [],
      "cargo_features": []
    },
    {
      "name": "rule_deposit_deposits",
      "expected_result": "Verified",
      "prover_options": [],
      "cargo_features": []
    },
    {
      "name": "rule_withdraw_withdraws",
      "expected_result": "Verified",
      "prover_options": [],
      "cargo_features": []
    },
    {
      "name": "rule_withdraw_does_not_revert",
      "expected_result": "Verified",
      "prover_options": [],
      "cargo_features": []
    },
    {
      "name": "rule_update_balance",
      "expected_result": "Verified",
      "prover_options": [],
      "cargo_features": []
    },
    {
      "name": "rule_deposit_base",
      "expected_result": "Verified",
      "prover_options": [],
      "cargo_features": []
    },
    {
      "name": "rule_deposit_quote",
      "expected_result": "Verified",
      "prover_options": [],
      "cargo_features": []
    },
    {
      "name": "rule_withdraw_base",
      "expected_result": "Verified",
      "prover_options": [],
      "cargo_features": []
    },
    {
      "name": "rule_withdraw_quote",
      "expected_result": "Verified",
      "prover_options": [],
      "cargo_features": []
    },
    {
      "name": "rule_cancel_order_by_index_ask",
      "expected_result": "Verified",
      "prover_options": [],
      "cargo_features": []
    },
    {
      "name": "rule_cancel_order_ask",
      "expected_result": "Verified",
      "prover_options": [],
      "cargo_features": []
    },
    {
      "name": "rule_cancel_order_by_index_no_revert_bid",
      "expected_result": "Verified",
      "prover_options": [],
      "cargo_features": []
    },
    {
      "name": "rule_cancel_order_by_index_no_revert_ask",
      "expected_result": "Verified",
      "prover_options": [],
      "cargo_features": []
    },
    {
      "name": "rule_place_single_order_canceled_bid",
      "expected_result": "Verified",
      "prover_options": [],
      "cargo_features": []
    },
    {
      "name": "rule_place_single_order_canceled_ask",
      "expected_result": "Verified",
      "prover_options": [],
      "cargo_features": []
    },
    {
      "name": "rule_place_single_order_unmatched_bid",
      "expected_result": "Verified",
      "prover_options": [],
      "cargo_features": []
    },
    {
      "name": "rule_place_single_order_unmatched_ask",
      "expected_result": "Verified",
      "prover_options": [],
      "cargo_features": []
    },
    {
      "name": "rule_place_single_order_full_match_bid",
      "expected_result": "Verified",
      "prover_options": [],
      "cargo_features": []
    },
    {
      "name": "rule_place_single_order_full_match_ask",
      "expected_result": "Verified",
      "prover_options": [],
      "cargo_features": []
    },
    {
      "name": "rule_place_single_order_partial_match_bid",
      "expected_result": "Verified",
      "prover_options": [],
      "cargo_features": []
    },
    {
      "name": "rule_place_single_order_partial_match_ask",
      "expected_result": "Verified",
      "prover_options": [],
      "cargo_features": []
    },
    {
      "name": "rule_market_claim_seat_once",
      "expected_result": "Verified",
      "prover_options": [],
      "cargo_features": []
    },
    {
      "name": "rule_market_claim_seat_twice_same_trader",
      "expected_result": "Verified",
      "prover_options": [],
      "cargo_features": []
    },
    {
      "name": "rule_market_claim_seat_twice_different_trader",
      "expected_result": "Verified",
      "prover_options": [],
      "cargo_features": []
    },
    {
      "name": "rule_rest_remaining_bid",
      "expected_result": "Verified",
      "prover_options": [],
      "cargo_features": []
    },
    {
      "name": "rule_rest_remaining_ask",
      "expected_result": "Verified",
      "prover_options": [],
      "cargo_features": []
    },
    {
      "name": "rule_market_release_seat",
      "expected_result": "Verified",
      "prover_options": [],
      "cargo_features": []
    },
    {
      "name": "rule_integrity_of_batch_update_cancel_bid",
      "expected_result": "Verified",
      "prover_options": [],
      "cargo_features": []
    },
    {
      "name": "rule_integrity_of_batch_update_cancel_ask",
      "expected_result": "Verified",
      "prover_options": [],
      "cargo_features": []
    },
    {
      "name": "rule_integrity_of_batch_update_cancel_hint_bid",
      "expected_result": "Verified",
      "prover_options": [],
      "cargo_features": []
    },
    {
      "name": "rule_integrity_of_batch_update_cancel_hint_ask",
      "expected_result": "Verified",
      "prover_options": [],
      "cargo_features": []
    },
    {
      "name": "rule_integrity_of_batch_update_place_order_bid",
      "expected_result": "Verified",
      "prover_options": [],
      "cargo_features": []
    },
    {
      "name": "rule_integrity_of_batch_update_place_order_ask",
      "expected_result": "Verified",
      "prover_options": [],
      "cargo_features": []
    },
    {
      "name": "rule_matching_if_maker_order_exists_bid",
      "expected_result": "Verified",
      "prover_options": [],
      "cargo_features": []
    },   
    {
      "name": "rule_matching_if_maker_order_exists_ask",
      "expected_result": "Verified",
      "prover_options": [],
      "cargo_features": []
    },   
    {
      "name": "rule_crossed_prices_if_matched_bid",
      "expected_result": "Verified",
      "prover_options": [],
      "cargo_features": []
    },   
    {
      "name": "rule_crossed_prices_if_matched_ask",
      "expected_result": "Verified",
      "prover_options": [],
      "cargo_features": []
    },   
    {
      "name": "rule_place_single_order_full_match_balances_bid",
      "expected_result": "Verified",
      "prover_options": [],
      "cargo_features": []
    },   
    {
      "name": "rule_place_single_order_full_match_balances_ask",
      "expected_result": "Verified",
      "prover_options": [],
      "cargo_features": []
    },   
    {
      "name": "rule_place_single_order_partial_match_balances_bid",
      "expected_result": "Verified",
      "prover_options": [],
      "cargo_features": []
    },   
    {
      "name": "rule_place_single_order_partial_match_balances_ask",
      "expected_result": "Verified",
      "prover_options": [],
      "cargo_features": []
    },   
    {
      "name": "rule_matching_order_removed_if_fully_matched_bid",
      "expected_result": "Verified",
      "prover_options": [],
      "cargo_features": []
    },   
    {
      "name": "rule_matching_order_removed_if_fully_matched_ask",
      "expected_result": "Verified",
      "prover_options": [],
      "cargo_features": []
    },   
    {
      "name": "rule_matching_fully_matched_if_order_removed_bid",
      "expected_result": "Verified",
      "prover_options": [],
      "cargo_features": []
    },   
    {
      "name": "rule_matching_fully_matched_if_order_removed_ask",
      "expected_result": "Verified",
      "prover_options": [],
      "cargo_features": []
    },   
    {
      "name": "rule_matching_decrease_maker_order_atoms_bid",
      "expected_result": "Verified",
      "prover_options": [],
      "cargo_features": []
    },   
    {
      "name": "rule_matching_decrease_maker_order_atoms_ask",
      "expected_result": "Verified",
      "prover_options": [],
      "cargo_features": []
    }
  ]
}
